python_zatobox/__init__.py
python_zatobox/iotconfig_pb2.py
python_zatobox/protobuff_schemas/.git
python_zatobox/protobuff_schemas/iotconfig.proto
python_zatobox/vanubus.py
python_zatobox-0.2.11.dist-info/METADATA
python_zatobox-0.2.11.dist-info/WHEEL
python_zatobox-0.2.11.dist-info/RECORD
