Metadata-Version: 2.1
Name: python-zatobox
Version: 0.2.11
Summary: 
Author: woutervanoverberghe
Author-email: wouter.vanoverberghe@vanutech.be
Requires-Python: >=3.10,<4.0
Classifier: Programming Language :: Python :: 3
Classifier: Programming Language :: Python :: 3.10
Classifier: Programming Language :: Python :: 3.11
Classifier: Programming Language :: Python :: 3.12
Classifier: Programming Language :: Python :: 3.13
Requires-Dist: protobuf (>=6.31.1,<7.0.0)
